{"i":"ве","r":[{"e":"благочести1въ","c":"благочестив","h":[{"t":"eusebes","g":"εὐσεβής"}]},{"e":"благочести1вэ","c":"благочестиве","i":2173,"h":[{"t":"eusebeo","g":"εὐσεβέω"}]},{"e":"благочести1внэ","c":"благочестивне","i":1019,"h":[{"t":"eusebos","g":"εὐσεβῶς"}]},{"e":"благочести1вный","c":"благочестивный","i":1018,"h":[{"t":"eusebes","g":"εὐσεβής"}]},{"e":"благочести1вw","c":"благочестиво","i":1020,"h":[{"t":"eusebos","g":"εὐσεβῶς"}]},{"e":"благочестивомyдреннw","c":"благочестивомудренно","i":1022,"h":[{"t":"eusebophronos","g":"εὐσεβοφρόνως"}]},{"e":"благочести1вый","c":"благочестивый","i":1021,"h":[{"t":"eusebes","g":"εὐσεβής"}]},{"e":"благочeстіе","c":"благочестие","i":1911,"h":[{"t":"eusebeia","g":"εὐσέβεια"}]}]}