{"i":"м","r":[{"c":"благовременен","h":[{"g":"εὔκαιρος","t":"eukairos"},{"g":"ἐπίκαιρος","t":"epikairos"}],"e":"благоврeмененъ"},{"i":2008,"c":"благовремение","h":[{"g":"εύκαιρία","t":"eukairia"},{"g":"εὐκαιρία","t":"eukairia"},{"g":"ἀφορμή","t":"aphorme"}],"e":"благоврeменіе"},{"i":2102,"c":"благовременне","h":[{"g":"εὐθέτως","t":"euthetos"},{"g":"εὐκαίρως","t":"eukairos"}],"e":"благоврeменнэ"},{"i":1944,"c":"благовременный","h":[{"g":"εὔκαιρος","t":"eukairos"},{"g":"ἐπίκαιρος","t":"epikairos"}],"e":"благоврeменный"}]}