{"i":"дж","r":[{"e":"богоуг0денъ","c":"богоугоден","h":[{"t":"thearestos","g":"θεάρεστος"},{"t":"peridexios","g":"περιδέξιος"}]},{"e":"богоуг0днэ","c":"богоугодне","i":1637,"h":[{"t":"thearestos","g":"θεαρέστως"}]},{"e":"богоуг0днw","c":"богоугодно","i":1636,"h":[{"t":"thearestos","g":"θεαρέστως"}]},{"e":"богоуг0дный","c":"богоугодный","i":1635,"h":[{"t":"thearestos","g":"θεάρεστος"},{"t":"peridexios","g":"περιδέξιος"}]},{"e":"богоугождaющій","c":"богоугождающий","i":2091,"h":[{"t":"enaresko","g":"ἐναρέσκω"}]}]}