{"r":[{"o":1,"p":"сущ.","e":"вaръ","i":2455,"h":[{"t":"kauson","g":"καύσων"}],"g":"жара","c":"вар"},{"h":[{"t":"barabbas","g":"βαραββᾶς"}],"e":"варaвва","i":2456,"c":"варавва"},{"h":[{"t":"barangos","g":"βάραγγος"}],"e":"варaггъ","c":"варагг"},{"h":[{"t":"baradatos","g":"βαραδάτος"}],"e":"варадaтъ","i":2458,"c":"варадат"},{"h":[{"t":"barak","g":"βαράκ"}],"e":"варaкъ","i":2459,"c":"варак"},{"h":[{"t":"barangos","g":"βάραγγος"}],"e":"варaнгъ","i":2457,"c":"варанг"},{"h":[{"t":"barachios","g":"βαράχιος"},{"t":"barachias","g":"βαραχίας"}],"e":"варaхій","i":2461,"c":"варахий"},{"h":[{"t":"barachisios","g":"βαραχίσιος"}],"e":"варахи1сій","i":2462,"c":"варахисий"},{"o":1,"p":"сущ.","e":"вaрваръ","i":2463,"h":[{"t":"barbaros","g":"βάρβαρος"}],"g":"иностранец","c":"варвар"},{"h":[{"t":"barbara","g":"βαρβάρα"}],"e":"варвaра","i":2464,"c":"варвара"},{"h":[{"t":"brasma","g":"βράσμα"},{"t":"hepsema","g":"ἕψημα"}],"e":"варeніе","i":2467,"c":"варение"},{"h":[{"t":"hepsema","g":"ἕψημα"},{"t":"opson","g":"ὄψον"}],"e":"вaриво","i":2469,"c":"вариво"},{"h":[{"t":"bariesous","g":"βαριησοῦς"}],"e":"варіисyсъ","i":2470,"c":"вариисус"},{"h":[{"t":"baripsabbas","g":"βαριψαββᾶς"},{"t":"baryzabas","g":"βαρυζαβᾶς"},{"t":"barypsabbas","g":"βαρυψαββᾶς"},{"t":"barypsabas","g":"βαρυψαβᾶς"}],"e":"варmpaвъ","i":2471,"c":"варипсав"},{"o":1,"p":"гл.","e":"вари1ти","i":2472,"h":[{"t":"proago","g":"προάγω"},{"t":"phthano","g":"φθάνω"}],"g":"предварять","c":"варити"},{"o":2,"p":"гл.","e":"вари1ти","i":3909,"h":[{"t":"hepso","g":"ἕψω"}],"g":"варить","c":"варити"},{"h":[{"t":"hepsomai","g":"ἕψομαι"}],"e":"вари1тисz","i":4480,"c":"варитися"},{"h":[{"t":"barlaam","g":"βαρλαάμ"}],"e":"варлаaмъ","i":2473,"c":"варлаам"},{"h":[{"t":"barnabas","g":"βαρνάβας"}],"e":"варнaва","i":2475,"c":"варнава"},{"h":[{"t":"barsabbas","g":"βαρσαββᾶς"}],"e":"варсaва","i":2477,"c":"варсава"},{"h":[{"t":"barses","g":"βαρσῆς"}],"e":"варсjсъ","i":2478,"c":"варсис"},{"h":[{"t":"barsanouphia","g":"βαρσανουφία"}],"e":"варсон0фіа","i":2480,"c":"варсонофиа"},{"h":[{"t":"barsanouphios","g":"βαρσανούφιος"}],"e":"варсон0фій","i":2479,"c":"варсонофий"},{"h":[{"t":"bartimaios","g":"βαρτιμαῖος"}],"e":"вартjмей","i":2481,"c":"вартимей"},{"h":[{"t":"barouch","g":"βαρούχ"}],"e":"варyхъ","i":2483,"c":"варух"},{"h":[{"t":"barouch","g":"βαρούχ"}],"e":"варyховъ","i":2484,"c":"варухов"},{"h":[{"t":"bartholomaios","g":"βαρθολομαῖος"}],"e":"варfоломeй","i":2485,"c":"варфоломей"},{"h":[{"t":"proago","g":"προάγω"}],"e":"варsти","i":2488,"c":"варяти"},{"h":[{"t":"proago","g":"προάγω"}],"e":"варsz","c":"варяя"}],"i":"авеилнстуфя"}