{"i":"н","r":[{"e":"вдохновeнъ","c":"вдохновен","h":[{"t":"diapneuo","g":"διαπνεύω"},{"t":"pneuo","g":"πνεύω"},{"t":"empneo","g":"ἐμπνέω"},{"t":"empneuo","g":"ἐμπνεύω"}]},{"e":"вдохновeніе","c":"вдохновение","i":1472,"h":[{"t":"physema","g":"φύσημα"},{"t":"epipnoia","g":"ἐπίπνοια"},{"t":"empneusis","g":"ἔμπνευσις"}]},{"e":"вдохнyвъ","c":"вдохнув","h":[{"t":"diapneuo","g":"διαπνεύω"},{"t":"pneuo","g":"πνεύω"},{"t":"empneo","g":"ἐμπνέω"},{"t":"empneuo","g":"ἐμπνεύω"}]},{"e":"вдохнyвсz","c":"вдохнувся","h":[{"t":"empneuomai","g":"ἐμπνεύομαι"}]},{"e":"вдохнyти","c":"вдохнути","i":1471,"h":[{"t":"diapneuo","g":"διαπνεύω"},{"t":"pneuo","g":"πνεύω"},{"t":"empneo","g":"ἐμπνέω"},{"t":"empneuo","g":"ἐμπνεύω"}]},{"e":"вдохнyтисz","c":"вдохнутися","i":1473,"h":[{"t":"empneuomai","g":"ἐμπνεύομαι"}]}]}