{"i":"иы","r":[{"c":"взяти","e":"взsти","h":[{"g":"αἱρέω","t":"haireo"},{"g":"αἴρω","t":"airo"},{"g":"βαστάζω","t":"bastazo"},{"g":"δέχομαι","t":"dechomai"},{"g":"δίδωμι","t":"didomi"},{"g":"διαίρω","t":"diairo"},{"g":"καταλαμβάνω","t":"katalambano"},{"g":"κρατάω","t":"kratao"},{"g":"λαμβάνω","t":"lambano"},{"g":"συλλαμβάνω","t":"syllambano"},{"g":"συναιρέω","t":"synaireo"},{"g":"ἀναλαμβάνω","t":"analambano"},{"g":"ἀπολαμβάνω","t":"apolambano"},{"g":"ἀποφέρω","t":"apophero"},{"g":"ἀφαιρέω","t":"aphaireo"},{"g":"ἐπαίρω","t":"epairo"},{"g":"ἐπιλαμβάνω","t":"epilambano"},{"g":"ἐπισπάω","t":"epispao"},{"g":"ἐφοδιάζομαι","t":"ephodiazomai"}],"i":2666},{"c":"взятие","e":"взsтіе","h":[{"g":"λῆμμα","t":"lemma"},{"g":"ἀφαίρησις","t":"aphairesis"},{"g":"ἄρσις","t":"arsis"},{"g":"ἔπαρσις","t":"eparsis"}],"i":2407},{"c":"взятися","e":"взsтисz","h":[{"g":"αἴρω","t":"airo"},{"g":"λαμβάνομαι","t":"lambanomai"},{"g":"ἀναλαμβάνω","t":"analambano"},{"g":"ἐκλαμβάνομαι","t":"eklambanomai"},{"g":"ἐνεπαίρω","t":"enepairo"},{"g":"ἐπαίρω","t":"epairo"},{"g":"ἑάλω","t":"healo"}],"i":2667},{"c":"взятый","e":"взsтый","h":[{"g":"αἱρέω","t":"haireo"},{"g":"αἴρω","t":"airo"},{"g":"βαστάζω","t":"bastazo"},{"g":"δέχομαι","t":"dechomai"},{"g":"δίδωμι","t":"didomi"},{"g":"διαίρω","t":"diairo"},{"g":"καταλαμβάνω","t":"katalambano"},{"g":"κρατάω","t":"kratao"},{"g":"λαμβάνω","t":"lambano"},{"g":"συλλαμβάνω","t":"syllambano"},{"g":"συναιρέω","t":"synaireo"},{"g":"ἀναλαμβάνω","t":"analambano"},{"g":"ἀπολαμβάνω","t":"apolambano"},{"g":"ἀποφέρω","t":"apophero"},{"g":"ἀφαιρέω","t":"aphaireo"},{"g":"ἐπαίρω","t":"epairo"},{"g":"ἐπιλαμβάνω","t":"epilambano"},{"g":"ἐπισπάω","t":"epispao"},{"g":"ἐφοδιάζομαι","t":"ephodiazomai"}]}]}