{"r":[{"h":[{"t":"rhetor","g":"ρήτωρ"}],"e":"витjа","i":2281,"c":"витиа"},{"h":[{"t":"rhetor","g":"ρήτωρ"}],"e":"витjй","c":"витий"},{"h":[{"t":"rhetor","g":"ρήτωρ"}],"e":"витjйскій","i":2282,"c":"витийский"},{"h":[{"t":"rhetoreia","g":"ρητορεία"}],"e":"витjйство","i":2283,"c":"витийство"},{"h":[{"t":"rhetoreuo","g":"ῥητορεύω"}],"e":"витjйствовати","i":2284,"c":"витийствовати"},{"h":[{"t":"rhetoreuo","g":"ῥητορεύω"}],"e":"витjйствуz","c":"витийствуя"},{"h":[{"t":"bitimios","g":"βιτίμιος"},{"t":"bitimion","g":"βιτιμίων"},{"t":"bytimios","g":"βυτίμιος"}],"e":"вmтjмій","i":2700,"c":"витимий"},{"h":[{"t":"rhetor","g":"ρήτωρ"}],"e":"витjz","c":"вития"}],"i":"аймя"}