{"i":"м","r":[{"c":"восприимъ, восприимь, восприимый","e":"воспріи1мъ, воспріи1мь, воспріи1мый","h":[{"g":"διανύω","t":"dianyo"},{"g":"καταδέχομαι","t":"katadechomai"},{"g":"κομίζομαι","t":"komizomai"},{"g":"λαμβάνω","t":"lambano"},{"g":"προσδέχομαι","t":"prosdechomai"},{"g":"προσλαμβάνομαι","t":"proslambanomai"},{"g":"προσλαμβάνω","t":"proslambano"},{"g":"ἀναλαμβάνω","t":"analambano"},{"g":"ἀντιλαμβάνομαι","t":"antilambanomai"},{"g":"ἀντιλαμβάνω","t":"antilambano"},{"g":"ἀπολαμβάνω","t":"apolambano"},{"g":"ἀπολαύω","t":"apolauo"},{"g":"ὑπέρχομαι","t":"hyperchomai"}]},{"c":"восприимати","e":"воспріимaти","h":[{"g":"δοξάζομαι","t":"doxazomai"},{"g":"εἰσδέχομαι","t":"eisdechomai"},{"g":"συναπολαύω","t":"synapolauo"},{"g":"ἀν­τιλαμβάνομαι","t":"antilambanomai"},{"g":"ἀναδέχομαι","t":"anadechomai"},{"g":"ἀναλαμβάνω","t":"analambano"},{"g":"ἀντιλαμβάνομαι","t":"antilambanomai"},{"g":"ἀπολαμβάνομαι","t":"apolambanomai"},{"g":"ἀπολαμβάνω","t":"apolambano"},{"g":"ὑποδέχομαι","t":"hypodechomai"}],"i":3352}]}