{"i":"адежи","r":[{"c":"воз(ж)женъ, возжженный","e":"воз(ж)жeнъ, возжжeнный","h":[{"g":"καίω","t":"kaio"},{"g":"πυρσεύω","t":"pyrseuo"},{"g":"ἀνάπτω","t":"anapto"},{"g":"ἅπτω","t":"hapto"},{"g":"ἐνπυριζω","t":"enpyrizo"}]},{"c":"возжадавый, возжа(ж)дав","e":"возжадaвый, возжа(ж)дaвъ","h":[{"g":"διψάω","t":"dipsao"},{"g":"πεινάω","t":"peinao"}]},{"c":"возжадати","e":"возжадaти","h":[{"g":"διψάω","t":"dipsao"},{"g":"πεινάω","t":"peinao"}],"i":2998},{"c":"возжадатися","e":"возжадaтисz","h":[{"g":"διψάω","t":"dipsao"},{"g":"ἐπιθυμέω","t":"epithymeo"}],"i":4374},{"c":"возжаждати","e":"возжаждaти","h":[{"g":"διψάω","t":"dipsao"},{"g":"πεινάω","t":"peinao"}]},{"c":"возжаждатися","e":"возжаждaтисz","h":[{"g":"διψάω","t":"dipsao"},{"g":"ἐπιθυμέω","t":"epithymeo"}]},{"c":"возжделевый, возжделев","e":"возжделёвый, возжделёвъ","h":[{"g":"ποθέω","t":"potheo"},{"g":"ἐπιθυμέω","t":"epithymeo"},{"g":"ἐπιποθέω","t":"epipotheo"},{"g":"ἐράομαι","t":"eraomai"},{"g":"ἐραστεύω","t":"erasteuo"}]},{"c":"возжделети","e":"возжделёти","h":[{"g":"ποθέω","t":"potheo"},{"g":"ἐπιθυμέω","t":"epithymeo"},{"g":"ἐπιποθέω","t":"epipotheo"},{"g":"ἐράομαι","t":"eraomai"},{"g":"ἐραστεύω","t":"erasteuo"}]},{"c":"возжег","e":"возжeгъ","h":[{"g":"καίω","t":"kaio"},{"g":"πυρσεύω","t":"pyrseuo"},{"g":"ἀνάπτω","t":"anapto"},{"g":"ἅπτω","t":"hapto"},{"g":"ἐνπυριζω","t":"enpyrizo"}]},{"c":"возжелавый, возжелав","e":"возжелaвый, возжелaвъ","h":[{"g":"ποθέω","t":"potheo"},{"g":"ἐπιθυμέω","t":"epithymeo"},{"g":"ἐπιποθέω","t":"epipotheo"}]},{"c":"возжелати","e":"возжелaти","h":[{"g":"ποθέω","t":"potheo"},{"g":"ἐπιθυμέω","t":"epithymeo"},{"g":"ἐπιποθέω","t":"epipotheo"}],"i":3002},{"c":"возжелевый, возжелев","e":"возжелёвый, возжелёвъ","h":[{"g":"ποθέω","t":"potheo"},{"g":"ἐπιθυμέω","t":"epithymeo"},{"g":"ἐπιποθέω","t":"epipotheo"},{"g":"ἐράομαι","t":"eraomai"},{"g":"ἐραστεύω","t":"erasteuo"}]},{"c":"возжеление","e":"возжелёніе","h":[{"g":"ἐπιθυμία","t":"epithymia"},{"g":"ὄρεξις","t":"orexis"}],"i":3003},{"c":"возжеленный, возжелен(ен)","e":"возжелённый, возжелён(ен)ъ","h":[{"g":"ποθέω","t":"potheo"},{"g":"ἐπιθυμέω","t":"epithymeo"},{"g":"ἐπιποθέω","t":"epipotheo"},{"g":"ἐράομαι","t":"eraomai"},{"g":"ἐραστεύω","t":"erasteuo"}]},{"c":"возжелети","e":"возжелёти","h":[{"g":"ποθέω","t":"potheo"},{"g":"ἐπιθυμέω","t":"epithymeo"},{"g":"ἐπιποθέω","t":"epipotheo"},{"g":"ἐράομαι","t":"eraomai"},{"g":"ἐραστεύω","t":"erasteuo"}]},{"c":"возжещи","e":"возжещи2","h":[{"g":"καίω","t":"kaio"},{"g":"πυρσεύω","t":"pyrseuo"},{"g":"ἀνάπτω","t":"anapto"},{"g":"ἅπτω","t":"hapto"},{"g":"ἐνπυριζω","t":"enpyrizo"}],"i":3006},{"c":"возжещися","e":"возжещи1сz","h":[{"g":"καίομαι","t":"kaiomai"},{"g":"ἀνάπτομαι","t":"anaptomai"},{"g":"ἀνάπτω","t":"anapto"}],"i":3007},{"c":"возжжение","e":"возжжeніе","h":[{"g":"ἐμπυρισμός","t":"empyrismos"}],"i":3008},{"c":"возжжещи","e":"возжжещи2","h":[{"g":"καίω","t":"kaio"},{"g":"πυρσεύω","t":"pyrseuo"},{"g":"ἀνάπτω","t":"anapto"},{"g":"ἅπτω","t":"hapto"},{"g":"ἐνπυριζω","t":"enpyrizo"}]},{"c":"возжжещися","e":"возжжещи1сz","h":[{"g":"καίομαι","t":"kaiomai"},{"g":"ἀνάπτομαι","t":"anaptomai"},{"g":"ἀνάπτω","t":"anapto"}]},{"c":"возживописати","e":"возживописaти","h":[{"g":"ἀναζωγραφέω","t":"anazographeo"}],"i":3009},{"c":"возжигаемь","e":"возжигaемь","h":[{"g":"ἀνάπτω","t":"anapto"},{"g":"ἐκκαίω","t":"ekkaio"}]},{"c":"возжигати","e":"возжигaти","h":[{"g":"ἀνάπτω","t":"anapto"},{"g":"ἐκκαίω","t":"ekkaio"}],"i":3010},{"c":"возжигая","e":"возжигaz","h":[{"g":"ἀνάπτω","t":"anapto"},{"g":"ἐκκαίω","t":"ekkaio"}]},{"c":"возжизати","e":"возжизaти","h":[{"g":"προσεπανάπτω","t":"prosepanapto"},{"g":"ἀνάπτω","t":"anapto"},{"g":"ἀναζέω","t":"anazeo"}],"i":3011},{"c":"возжизая","e":"возжизaz","h":[{"g":"προσεπανάπτω","t":"prosepanapto"},{"g":"ἀνάπτω","t":"anapto"},{"g":"ἀναζέω","t":"anazeo"}]},{"c":"возжиляти","e":"возжилsти","h":[{"g":"νευρόω","t":"neuroo"}],"i":3012}]}