{"r":[{"h":[{"t":"proskephalaion","g":"προσκεφάλαιον"}],"e":"возглaвіе","i":2926,"c":"возглавие"},{"h":[{"t":"proskephalaion","g":"προσκεφάλαιον"}],"e":"возглaвійца","i":4565,"c":"возглавийца"},{"h":[{"t":"anakephalaioo","g":"ἀνακεφαλαιόω"}],"e":"возглaвити","i":2927,"c":"возглавити"},{"h":[{"t":"proskephalaion","g":"προσκεφάλαιον"}],"e":"возглaвница","i":2928,"c":"возглавница"},{"h":[{"t":"kategoreo","g":"κατηγορέω"},{"t":"laleo","g":"λαλέω"}],"e":"возглаг0лати","i":2929,"c":"возглаголати"},{"h":[{"t":"laloumai","g":"λαλοῦμαι"}],"e":"возглаг0латисz","i":2930,"c":"возглаголатися"},{"h":[{"t":"kategoreo","g":"κατηγορέω"},{"t":"laleo","g":"λαλέω"}],"e":"возглаг0лz","c":"возглаголя"},{"h":[{"t":"ekphonesis","g":"ἐκφώνησις"}],"e":"возглaсъ","i":2931,"c":"возглас"},{"h":[{"t":"bombeo","g":"βομβέω"},{"t":"prosphoneo","g":"προσφωνέω"},{"t":"phoneo","g":"φωνέω"},{"t":"exephoneo","g":"ἐξεφωνέω"},{"t":"epiphoneo","g":"ἐπιφωνέω"},{"t":"echeo","g":"ἠχέω"}],"e":"возгласи1вый, возгласи1въ, возглaшь","c":"возгласивый, возгласивъ, возглашь"},{"h":[{"t":"bombeo","g":"βομβέω"},{"t":"prosphoneo","g":"προσφωνέω"},{"t":"phoneo","g":"φωνέω"},{"t":"exephoneo","g":"ἐξεφωνέω"},{"t":"epiphoneo","g":"ἐπιφωνέω"},{"t":"echeo","g":"ἠχέω"}],"e":"возгласи1ти","i":2932,"c":"возгласити"},{"h":[{"t":"exephonoumai","g":"ἐξεφωνοῦμαι"},{"t":"execheomai","g":"ἐξηχέομαι"}],"e":"возгласи1тисz","i":2933,"c":"возгласитися"},{"h":[{"t":"prosphoneo","g":"προσφωνέω"},{"t":"semaino","g":"σημαίνω"},{"t":"phoneo","g":"φωνέω"},{"t":"enecheo","g":"ἐνηχέω"},{"t":"epiphoneo","g":"ἐπιφωνέω"},{"t":"hypophoneo","g":"ὑποφωνέω"}],"e":"возглашaти","i":2935,"c":"возглашати"}],"i":"вгсш"}