{"r":[{"c":"возблаговолити","e":"возблаговоли1ти","h":[{"g":"εὐδοκέω","t":"eudokeo"}],"i":4553},{"e":"возблагодари1въ","h":[{"g":"εὐχαριστέω","t":"eucharisteo"},{"g":"ἀποδέχομαι","t":"apodechomai"}],"c":"возблагодарив"},{"c":"возблагодарити","e":"возблагодари1ти","h":[{"g":"εὐχαριστέω","t":"eucharisteo"},{"g":"ἀποδέχομαι","t":"apodechomai"}],"i":2867},{"c":"возблагодетельствовати","e":"возблагодётельствовати","h":[{"g":"εὐεργετέω","t":"euergeteo"}],"i":2868},{"c":"возблагодушествовати","e":"возблагодyшествовати","h":[{"g":"ἐπευθυμέω","t":"epeuthymeo"}],"i":4554},{"c":"возблагопутствити","e":"возблагопyтствити","h":[{"g":"εὐοδόω","t":"euodoo"}],"i":2869},{"c":"возблагословити","e":"возблагослови1ти","h":[{"g":"εὐλογέω","t":"eulogeo"}],"i":2870},{"c":"возблагословитися","e":"возблагослови1тисz","h":[{"g":"ἐνευλογέομαι","t":"eneulogeomai"},{"g":"ἐνευλογίζομαι","t":"eneulogizomai"}],"i":2871},{"c":"возблажати","e":"возблажaти","h":[{"g":"ἀγαθύνομαι","t":"agathynomai"}],"i":4555},{"e":"возблистaвъ","h":[{"g":"ἀπαστράπτω","t":"apastrapto"},{"g":"ἐξαστράπτω","t":"exastrapto"}],"c":"возблистав"},{"c":"возблистати","e":"возблистaти","h":[{"g":"ἀπαστράπτω","t":"apastrapto"},{"g":"ἐξαστράπτω","t":"exastrapto"}],"i":2873},{"c":"возблудити","e":"возблуди1ти","h":[{"g":"ἐξπορνεύω","t":"exporneuo"}],"i":4556}],"i":"аиу"}