{"i":"джп","r":[{"e":"возроди1въ","c":"возродив","h":[{"t":"anagennao","g":"ἀναγεννάω"}]},{"e":"возроди1всz","c":"возродився","h":[{"t":"anagennaomai","g":"ἀναγεννάομαι"}]},{"e":"возроди1ти","c":"возродити","i":3125,"h":[{"t":"anagennao","g":"ἀναγεννάω"}]},{"e":"возроди1тисz","c":"возродитися","i":3126,"h":[{"t":"anagennaomai","g":"ἀναγεννάομαι"}]},{"e":"возрождeніе","c":"возрождение","i":3127,"h":[{"t":"anagennesis","g":"ἀναγέννησις"}]},{"e":"возроптaти","c":"возроптати","i":4593,"h":[{"t":"gongyzo","g":"γογγύζω"},{"t":"diagongyzo","g":"διαγογγύζω"}]}]}