{"i":"лнт","r":[{"i":4576,"h":[{"t":"spondeion","g":"σπονδεῖον"}],"c":"возлиялник","e":"возліsлникъ"},{"i":4678,"h":[{"t":"spondeion","g":"σπονδεῖον"}],"c":"возлиялница","e":"возліsлница"},{"i":3035,"h":[{"t":"proschysis","g":"πρόσχυσις"},{"t":"sponde","g":"σπονδή"}],"c":"возлияние","e":"возліsніе"},{"i":3036,"h":[{"t":"ballo","g":"βάλλω"},{"t":"katacheo","g":"καταχέω"},{"t":"spendo","g":"σπένδω"},{"t":"epicheo","g":"ἐπιχέω"}],"c":"возлияти","e":"возліsти"},{"i":3037,"h":[{"t":"pericheo","g":"περιχέω"},{"t":"hypercheomai","g":"ὑπερχέομαι"}],"c":"возлиятися","e":"возліsтисz"}]}