{"r":[{"e":"возшeдый (возшeдъ, восшeдъ)","h":[{"g":"διέρχομαι","t":"dierchomai"},{"g":"πορεύομαι","t":"poreuomai"},{"g":"ἀνέρχομαι","t":"anerchomai"},{"g":"ἀναβαίνω","t":"anabaino"},{"g":"ἀνατέλλω","t":"anatello"}],"c":"возшедый (возшедъ, восшедъ)"},{"e":"возшeлъ (возшлA, возшли2, взошeлъ)","h":[{"g":"διέρχομαι","t":"dierchomai"},{"g":"πορεύομαι","t":"poreuomai"},{"g":"ἀνέρχομαι","t":"anerchomai"},{"g":"ἀναβαίνω","t":"anabaino"},{"g":"ἀνατέλλω","t":"anatello"}],"c":"возшелъ (возшла, возшли, взошелъ)"},{"c":"возшествие","e":"возшeствіе","h":[{"g":"ἀνάβασις","t":"anabasis"}],"i":3173},{"e":"возшумёвъ","h":[{"g":"βομβέω","t":"bombeo"},{"g":"περιηχέω","t":"periecheo"},{"g":"ἠχέω","t":"echeo"}],"c":"возшумев"},{"c":"возшумети","e":"возшумёти","h":[{"g":"βομβέω","t":"bombeo"},{"g":"περιηχέω","t":"periecheo"},{"g":"ἠχέω","t":"echeo"}],"i":3174}],"i":"еу"}