{"r":[{"t":"abramiaios","g":"άβραμιαῖος","r":[{"i":32,"e":"ґвраaмскій","c":"авраамский"}]},{"t":"abel","g":"ἀβέλ","r":[{"i":14,"e":"ѓвель","c":"авель"}]},{"t":"aberkios","g":"ἀβέρκιος","r":[{"i":1737,"e":"ґвeркіевъ","c":"аверкиев"},{"i":18,"e":"ґвeркій","c":"аверкий"}]},{"t":"abepas","g":"ἀβήπας","r":[{"i":1746,"e":"ґвЂпъ","c":"авип"}]},{"t":"abana","g":"ἀβανά","r":[{"i":382,"e":"ґрванA","c":"арвана"}]},{"t":"abbakoum","g":"ἀββακούμ","r":[{"i":6,"e":"ґввакyмъ","c":"аввакум"}]},{"t":"abbakyros","g":"ἀββακύρος","r":[{"i":8,"e":"ґввакЂръ","c":"аввакир"}]},{"t":"abba","g":"ἀββᾶ","r":[{"i":5,"e":"ѓвва","c":"авва"}]},{"t":"abbas","g":"ἀββᾶς","r":[{"i":5,"e":"ѓвва","c":"авва"}]},{"t":"abdias","g":"ἀβδίας","r":[{"i":10,"e":"ґвдjй","c":"авдий"}]},{"t":"abdaeos","g":"ἀβδαέος","r":[{"i":1730,"e":"ѓvда","c":"авда"}]},{"t":"abdas","g":"ἀβδας","r":[{"i":1730,"e":"ѓvда","c":"авда"}]},{"t":"abdenago","g":"ἀβδεναγώ","r":[{"i":9,"e":"ґвденагw2","c":"авденаго"}]},{"t":"abdiesous","g":"ἀβδιησοῦς","r":[{"i":1733,"e":"ґvдіeсъ","c":"авдиес"},{"i":1734,"e":"ґvдjкій","c":"авдикий"}]},{"t":"abdon","g":"ἀβδών","r":[{"i":1736,"e":"ґвд0нъ","c":"авдон"}]},{"t":"abdas","g":"ἀβδᾶς","r":[{"i":1730,"e":"ѓvда","c":"авда"}]},{"t":"abeim","g":"ἀβείμ","r":[{"i":22,"e":"ґвjмъ","c":"авим"}]},{"t":"abeddara","g":"ἀβεδδαρά","r":[{"i":11,"e":"ґведдaръ","c":"аведдар"}]},{"t":"abeiron","g":"ἀβειρών","r":[{"i":25,"e":"ґвірHнъ","c":"авирон"}]},{"t":"abener","g":"ἀβενήρ","r":[{"i":16,"e":"ґвени1ръ","c":"авенир"}]},{"t":"abenner","g":"ἀβεννήρ","r":[{"i":16,"e":"ґвени1ръ","c":"авенир"},{"i":17,"e":"ґвени1ровъ","c":"авениров"}]},{"t":"abessalom","g":"ἀβεσσαλώμ","r":[{"i":19,"e":"ґвессалHмъ","c":"авессалом"}]},{"t":"abia","g":"ἀβιά","r":[{"i":1738,"e":"ґвjа","c":"авиа"},{"i":1739,"e":"ґвіaнь","c":"авиань"}]},{"t":"abiathar","g":"ἀβιαθάρ","r":[{"i":1740,"e":"ґвіаfaръ","c":"авиафар"}]},{"t":"abilene","g":"ἀβιληνή","r":[{"i":21,"e":"ґвілинjz","c":"авилиния"}]},{"t":"abimelech","g":"ἀβιμέλεχ","r":[{"i":23,"e":"ґвімелeхъ","c":"авимелех"}]},{"t":"abioud","g":"ἀβιούδ","r":[{"i":26,"e":"ґвіyдъ","c":"авиуд"}]},{"t":"abiron","g":"ἀβιρών","r":[{"i":25,"e":"ґвірHнъ","c":"авирон"}]},{"t":"ablabios","g":"ἀβλάβιος","r":[{"i":27,"e":"ґвлaвій","c":"авлавий"}]},{"t":"ablabos","g":"ἀβλαβῶς","r":[{"i":825,"e":"безврeднw","c":"безвредно"}]}],"i":"abdeilory"}