{"r":[{"r":[{"c":"акафист","i":97,"e":"ґкafістъ"}],"t":"akathistos","g":"ἀκάθιστος"},{"r":[{"c":"акакий","i":96,"e":"ґкaкій"}],"t":"akakios","g":"ἀκάκιος"},{"r":[{"c":"безсердечный","i":2029,"e":"безсердeчный"}],"t":"akardios","g":"ἀκάρδιος"},{"r":[{"c":"безглавный","i":1671,"e":"безглaвный"}],"t":"akephalos","g":"ἀκέφαλος"},{"r":[{"c":"акиндин","i":104,"e":"ґкіндЂнъ"},{"c":"безбедный","i":1650,"e":"безбёдный"}],"t":"akindynos","g":"ἀκίνδυνος"},{"r":[{"c":"безвременне","i":1668,"e":"безврeменнэ"},{"c":"безвременно","i":1669,"e":"безврeменнw"}],"t":"akairos","g":"ἀκαίρως"},{"r":[{"c":"безвременномечтанный","i":1670,"e":"безвременномечтaнный"}],"t":"akairophantastos","g":"ἀκαιροφάνταστος"},{"r":[{"c":"беззлобие","i":492,"e":"безѕл0біе"}],"t":"akakia","g":"ἀκακία"},{"r":[{"c":"безплодие","i":1692,"e":"безпл0діе"},{"c":"безплодствие","i":1693,"e":"безпл0дствіе"}],"t":"akarpia","g":"ἀκαρπία"},{"r":[{"c":"беззазорный","i":830,"e":"беззаз0рный"}],"t":"akatagnostos","g":"ἀκατάγνωστος"},{"r":[{"c":"безпрестанный","i":507,"e":"безпрестaнный"}],"t":"akatapaustos","g":"ἀκατάπαυστος"},{"r":[{"c":"акелдама","i":99,"e":"ґкелдамA"}],"t":"akeldamach","g":"ἀκελδαμάχ"},{"r":[{"c":"акепсий","i":1768,"e":"ґкеpjй"}],"t":"akepsees","g":"ἀκεψεής"},{"r":[{"c":"акепсима","i":100,"e":"ґкеpjма"}],"t":"akepsimas","g":"ἀκεψιμᾶς"},{"r":[{"c":"безбедне","i":1653,"e":"безбёднэ"},{"c":"безбедно","i":1652,"e":"безбёднw"}],"t":"akindynos","g":"ἀκινδύνως"},{"r":[{"c":"вследствовати","i":3783,"e":"вслёдствовати"}],"t":"akoloutheo","g":"ἀκολουθέω"},{"r":[{"c":"акутион","i":1774,"e":"ґкутjHнъ"}],"t":"akoution","g":"ἀκουτίων"},{"r":[{"c":"акутион","i":1774,"e":"ґкутjHнъ"}],"t":"akoutios","g":"ἀκούτιος"},{"r":[{"c":"акрид","i":3920,"e":"ґкрjдъ"}],"t":"akris","g":"ἀκρίς"},{"r":[{"c":"верховник","i":2600,"e":"верх0вникъ"}],"t":"akraimon","g":"ἀκραίμων"},{"r":[{"c":"акрагантийский","i":1769,"e":"ґкрагантjйскій"}],"t":"akragantinos","g":"ἀκραγαντῖνος"},{"r":[{"c":"верхостреляние","i":2602,"e":"верхострэлsніе"}],"t":"akrobolisis","g":"ἀκροβόλισις"},{"r":[{"c":"верх","i":1490,"e":"вeрхъ"}],"t":"akrothinion","g":"ἀκροθίνιον"},{"r":[{"c":"акростих","i":1770,"e":"ґкростjхъ"}],"t":"akrostichis","g":"ἀκροστιχίς"},{"r":[{"c":"верховник","i":2600,"e":"верх0вникъ"}],"t":"akropolis","g":"ἀκρόπολις"},{"r":[{"c":"верховный","i":2601,"e":"верх0вный"}],"t":"akros","g":"ἀκρός"},{"r":[{"c":"верх","i":1490,"e":"вeрхъ"}],"t":"akrotes","g":"ἀκρότης"},{"r":[{"c":"акилина","i":107,"e":"ґкmлjна"}],"t":"akylina","g":"ἀκυλίνα"},{"r":[{"c":"безволненне","i":823,"e":"безв0лненнэ"},{"c":"безволненно","i":821,"e":"безв0лненнw"}],"t":"akymantos","g":"ἀκυμάντως"},{"r":[{"c":"блудный","i":1144,"e":"блyдный"}],"t":"akolastos","g":"ἀκόλαστος"}],"i":"aeiory"}