{"i":"aio","r":[{"t":"akris","r":[{"e":"ґкрjдъ","c":"акрид","i":3920}],"g":"ἀκρίς"},{"t":"akraimon","r":[{"e":"верх0вникъ","c":"верховник","i":2600}],"g":"ἀκραίμων"},{"t":"akragantinos","r":[{"e":"ґкрагантjйскій","c":"акрагантийский","i":1769}],"g":"ἀκραγαντῖνος"},{"t":"akrobolisis","r":[{"e":"верхострэлsніе","c":"верхостреляние","i":2602}],"g":"ἀκροβόλισις"},{"t":"akrothinion","r":[{"e":"вeрхъ","c":"верх","i":1490}],"g":"ἀκροθίνιον"},{"t":"akrostichis","r":[{"e":"ґкростjхъ","c":"акростих","i":1770}],"g":"ἀκροστιχίς"},{"t":"akropolis","r":[{"e":"верх0вникъ","c":"верховник","i":2600}],"g":"ἀκρόπολις"},{"t":"akros","r":[{"e":"верх0вный","c":"верховный","i":2601}],"g":"ἀκρός"},{"t":"akrotes","r":[{"e":"вeрхъ","c":"верх","i":1490}],"g":"ἀκρότης"},{"t":"akron","r":[{"e":"вeрхъ","c":"верх","i":1490}],"g":"ἄκρον"}]}