{"r":[{"r":[{"c":"восприимати","i":3352,"e":"воспріимaти"}],"t":"apolambanomai","g":"ἀπολαμβάνομαι"},{"r":[{"c":"благовосприяти","i":889,"e":"благовоспріsти"},{"c":"взимати","i":2660,"e":"взимaти"},{"c":"взяти","i":2666,"e":"взsти"},{"c":"восприимати","i":3352,"e":"воспріимaти"},{"c":"восприяти","i":3353,"e":"воспріsти"}],"t":"apolambano","g":"ἀπολαμβάνω"},{"r":[{"c":"восприяти","i":3353,"e":"воспріsти"}],"t":"apolauo","g":"ἀπολαύω"},{"r":[{"c":"аполлинарий","i":258,"e":"ґполлінaрій"}],"t":"apolinarios","g":"ἀπολινάριος"},{"r":[{"c":"аполлинарий","i":258,"e":"ґполлінaрій"}],"t":"apollinarios","g":"ἀπολλινάριος"},{"r":[{"c":"аполлинариа","i":259,"e":"ґполлінaріа"}],"t":"apollinaria","g":"ἀπολλιναρία"},{"r":[{"c":"аполлинариане","i":260,"e":"ґполлінаріaне"}],"t":"apollinarioi","g":"ἀπολλιναριοί"},{"r":[{"c":"аполлониа","i":261,"e":"ґполлHніа"},{"c":"аполониада","i":266,"e":"ґполоніaда"}],"t":"apollonia","g":"ἀπολλωνία"},{"r":[{"c":"аполлоний","i":262,"e":"ґполлHній"}],"t":"apollonios","g":"ἀπολλώνιος"},{"r":[{"c":"аполлос","i":264,"e":"ґполлHсъ"}],"t":"apollos","g":"ἀπολλῶς"},{"r":[{"c":"восприятие","i":3354,"e":"воспріsтіе"}],"t":"apolausis","g":"ἀπόλαυσις"},{"r":[{"c":"аполлон","i":1810,"e":"ґполлHнъ"}],"t":"apollon","g":"ἀπόλλων"},{"r":[{"c":"безсоветие","i":1703,"e":"безсовётіе"}],"t":"apoleia","g":"ἀπώλεια"}],"i":"aeil"}