{"i":"deklmpst","r":[{"g":"ἀρχίλαος","r":[{"i":1828,"c":"архилий","e":"ґрхілjй"}],"t":"archilaos"},{"g":"ἀρχίλιος","r":[{"i":1828,"c":"архилий","e":"ґрхілjй"}],"t":"archilios"},{"g":"ἀρχιδιάκονος","r":[{"i":194,"c":"архидиакон","e":"ґрхідіaконъ"}],"t":"archidiakonos"},{"g":"ἀρχιεπίσκοπος","r":[{"i":391,"c":"архиепископ","e":"ґрхіепjскопъ"}],"t":"archiepiskopos"},{"g":"ἀρχιεράρχης","r":[{"i":392,"c":"архиерарх","e":"ґрхіерaрхъ"}],"t":"archierarches"},{"g":"ἀρχιερέας","r":[{"i":424,"c":"архиерей","e":"ґрхіерeй"}],"t":"archiereas"},{"g":"ἀρχιερατεύω","r":[{"i":429,"c":"архиерействовати","e":"ґрхіерeйствовати"}],"t":"archierateuo"},{"g":"ἀρχιερατικός","r":[{"i":427,"c":"архиерейский","e":"ґрхіерeйскій"}],"t":"archieratikos"},{"g":"ἀρχιερεύς","r":[{"i":424,"c":"архиерей","e":"ґрхіерeй"}],"t":"archiereus"},{"g":"ἀρχικός","r":[{"i":839,"c":"безначальный","e":"безначaльный"}],"t":"archikos"},{"g":"ἀρχιμαδτρίτης","r":[{"i":430,"c":"архимандрит","e":"ґрхімандрjтъ"}],"t":"archimadtrites"},{"g":"ἀρχιμανδρίτης","r":[{"i":430,"c":"архимандрит","e":"ґрхімандрjтъ"}],"t":"archimandrites"},{"g":"ἀρχιποίμην","r":[{"i":425,"c":"архипастырь","e":"ґрхіпaстырь"}],"t":"archipoimen"},{"g":"ἀρχιστράτηγος","r":[{"i":195,"c":"архистратиг","e":"ґрхістрати1гъ"},{"i":2853,"c":"воевода","e":"воев0да"},{"i":4549,"c":"вождоначалник","e":"вождоначaлникъ"}],"t":"archistrategos"},{"g":"ἀρχισυνάγωγος","r":[{"i":196,"c":"архисинагог","e":"ґрхісmнагHгъ"}],"t":"archisynagogos"},{"g":"ἀρχιτέκτων","r":[{"i":198,"c":"архитектон","e":"ґрхітeктwнъ"}],"t":"architekton"},{"g":"ἀρχιτρίκλινος","r":[{"i":432,"c":"архитриклин","e":"ґрхітріклjнъ"}],"t":"architriklinos"},{"g":"ἄρχιππος","r":[{"i":310,"c":"архипп","e":"ґрхjппъ"}],"t":"archippos"}]}