{"r":[{"t":"arabissa","r":[{"e":"ґрaвлzнынz","i":274,"c":"аравляныня"}],"g":"ἀράβισσα"},{"t":"aram","r":[{"e":"ґрaмъ","i":277,"c":"арам"}],"g":"ἀράμ"},{"t":"arachios","r":[{"e":"ґрахjй","i":281,"c":"арахий"}],"g":"ἀράχιος"},{"t":"arethas","r":[{"e":"ґрefа","i":284,"c":"арефа"}],"g":"ἀρέθας"},{"t":"arepha","r":[{"e":"ґрefа","i":284,"c":"арефа"}],"g":"ἀρέφα"},{"t":"aren","r":[{"e":"ѓгнецъ","i":59,"c":"агнец"}],"g":"ἀρήν"},{"t":"aristarchos","r":[{"e":"ґрістaрхъ","i":292,"c":"аристарх"}],"g":"ἀρίσταρχος"},{"t":"arabia","r":[{"e":"ґравjа","i":271,"c":"аравиа"}],"g":"ἀραβία"},{"t":"arabos","r":[{"e":"ґрави1тскій","i":270,"c":"аравитский"}],"g":"ἀραβός"},{"t":"arbana","r":[{"e":"ґрванA","i":382,"c":"арвана"}],"g":"ἀρβανά"},{"t":"ardalion","r":[{"e":"ґрдаліHнъ","i":1814,"c":"ардалион"}],"g":"ἀρδαλίων"},{"t":"areianoi","r":[{"e":"ґріaне","i":1818,"c":"ариане"},{"e":"ґріани1ты","i":286,"c":"арианиты"}],"g":"ἀρειανοί"},{"t":"areiophron","r":[{"e":"ґріемyдрственный","i":183,"c":"ариемудрственный"}],"g":"ἀρειόφρων"},{"t":"arephousios","r":[{"e":"ґреfусjйскій","i":1815,"c":"арефусийский"}],"g":"ἀρεφούσιος"},{"t":"ariadne","r":[{"e":"ґріaдна","i":1817,"c":"ариадна"}],"g":"ἀριάδνη"},{"t":"aridelos","r":[{"e":"богоzвлeннw","i":1387,"c":"богоявленно"}],"g":"ἀριδήλως"},{"t":"arimathaia","r":[{"g":"топоним","c":"аримафей","p":"сущ.","e":"ґрімаfeй","i":3956,"o":2}],"g":"ἀριμαθαία"},{"t":"arimathaias","r":[{"g":"Иосиф","c":"аримафей","p":"сущ.","e":"ґрімаfeй","i":291,"o":1}],"g":"ἀριμαθαίας"},{"t":"arimatheias","r":[{"g":"Иосиф","c":"аримафей","p":"сущ.","e":"ґрімаfeй","i":291,"o":1}],"g":"ἀριμαθείας"},{"t":"aristion","r":[{"e":"ґрістіHнъ","i":1819,"c":"аристион"}],"g":"ἀριστίων"},{"t":"aristeuo","r":[{"e":"воевaти","i":2852,"c":"воевати"}],"g":"ἀριστεύω"},{"t":"aristoboulos","r":[{"e":"ґрістовyлъ","i":293,"c":"аристовул"}],"g":"ἀριστοβοῦλος"},{"t":"aristoboulos","r":[{"e":"ґрістовyлъ","i":293,"c":"аристовул"}],"g":"ἀριστόβουλος"},{"t":"aristokleos","r":[{"e":"ґрістоклjй","i":1820,"c":"аристоклий"}],"g":"ἀριστόκλεος"},{"t":"arkadios","r":[{"e":"ґркaдій","i":294,"c":"аркадий"}],"g":"ἀρκάδιος"},{"t":"armenios","r":[{"e":"ґрмени1нъ","i":1823,"c":"арменин"},{"e":"ґрмeнскій","i":298,"c":"арменский"}],"g":"ἀρμένιος"},{"t":"armathem","r":[{"e":"ґрмаfeма","i":385,"c":"армафема"}],"g":"ἀρμαθέμ"},{"t":"armathaim","r":[{"e":"ґрмаfeма","i":385,"c":"армафема"}],"g":"ἀρμαθαίμ"},{"t":"armenia","r":[{"e":"ґрмeніа","i":297,"c":"армениа"}],"g":"ἀρμενία"},{"t":"arnion","r":[{"e":"ѓгнецъ","i":59,"c":"агнец"},{"e":"ѓгнz","i":62,"c":"агня"}],"g":"ἀρνίον"}],"i":"abcdefikmnoprst"}