{"i":"pr","r":[{"g":"ἀρχιεπίσκοπος","r":[{"c":"архиепископ","e":"ґрхіепjскопъ","i":391}],"t":"archiepiskopos"},{"g":"ἀρχιεράρχης","r":[{"c":"архиерарх","e":"ґрхіерaрхъ","i":392}],"t":"archierarches"},{"g":"ἀρχιερέας","r":[{"c":"архиерей","e":"ґрхіерeй","i":424}],"t":"archiereas"},{"g":"ἀρχιερατεύω","r":[{"c":"архиерействовати","e":"ґрхіерeйствовати","i":429}],"t":"archierateuo"},{"g":"ἀρχιερατικός","r":[{"c":"архиерейский","e":"ґрхіерeйскій","i":427}],"t":"archieratikos"},{"g":"ἀρχιερεύς","r":[{"c":"архиерей","e":"ґрхіерeй","i":424}],"t":"archiereus"}]}