{"i":"aeoy","r":[{"r":[{"i":208,"c":"ассарий","e":"ґссaрій"}],"t":"assarion","g":"ἀσσάριον"},{"r":[{"i":314,"c":"асенефа","e":"ґсенefа"}],"t":"asseneth","g":"ἀσσενέθ"},{"r":[{"i":435,"c":"ассур","e":"ґссyръ"}],"t":"assour","g":"ἀσσούρ"},{"r":[{"i":314,"c":"асенефа","e":"ґсенefа"}],"t":"assyneth","g":"ἀσσυνέθ"},{"r":[{"i":434,"c":"ассириа","e":"ґссmрjа"}],"t":"assyria","g":"ἀσσύρια"},{"r":[{"i":434,"c":"ассириа","e":"ґссmрjа"},{"i":447,"c":"ассирианин","e":"ґссmрjанинъ"}],"t":"assyrios","g":"ἀσσύριος"},{"r":[{"i":437,"c":"ассон","e":"ѓссонъ"}],"t":"asson","g":"ἆσσον"},{"r":[{"i":437,"c":"ассон","e":"ѓссонъ"}],"t":"assos","g":"ἆσσος"}]}