{"i":"inorsy","r":[{"t":"beroia","r":[{"e":"бeріа","c":"бериа","i":1722},{"e":"вeрріа","c":"верриа","i":1486}],"g":"βέροια"},{"t":"berrhoia","r":[{"e":"вeрріа","c":"верриа","i":1486}],"g":"βέρροια"},{"t":"berrhoia","r":[{"e":"вeрріа","c":"верриа","i":1486}],"g":"βέῤῥοια"},{"t":"berina","r":[{"e":"вирінeа","c":"виринеа","i":2276}],"g":"βερίνα"},{"t":"berine","r":[{"e":"вирінeа","c":"виринеа","i":2276}],"g":"βερίνη"},{"t":"bernike","r":[{"e":"вернікjа","c":"верникиа","i":2588}],"g":"βερνίκη"},{"t":"beroiaios","r":[{"e":"бeрzнинъ","c":"берянин","i":1723}],"g":"βεροιαῖος"},{"t":"beronike","r":[{"e":"веронjка","c":"вероника","i":2596}],"g":"βερονίκη"},{"t":"bersabee","r":[{"i":2690,"o":2,"g":"топоним","e":"вирсавjа","c":"вирсавиа","p":"сущ."},{"i":6047,"o":1,"g":"имя","e":"вирсавjа","c":"вирсавиа","p":"сущ."}],"g":"βηρσαβεέ"},{"t":"berytos","r":[{"e":"виfyтъ","c":"вифут","i":2312}],"g":"βηρυτός"}]}