{"i":"aeioy","r":[{"g":"βράσις","r":[{"c":"врение","e":"врёніе","i":3477}],"t":"brasis"},{"g":"βράσμα","r":[{"c":"варение","e":"варeніе","i":2467},{"c":"врение","e":"врёніе","i":3477}],"t":"brasma"},{"g":"βρίγγας","r":[{"c":"вринга","e":"врjнга","i":3484}],"t":"bringas"},{"g":"βραβεύομαι","r":[{"c":"водворятися","e":"водворsтисz","i":2831}],"t":"brabeuomai"},{"g":"βρασμός","r":[{"c":"возврение","e":"возврёніе","i":2917}],"t":"brasmos"},{"g":"βρεττανίς","r":[{"c":"вританиа","e":"вритaніа","i":3486}],"t":"brettanis"},{"g":"βροντάω","r":[{"c":"возгремети","e":"возгремёти","i":2949},{"c":"гремети","e":"гремёти","i":4316}],"t":"brontao"},{"g":"βροντή","r":[{"c":"гремение","e":"гремёніе","i":4315},{"c":"гром","e":"гр0мъ","i":4350}],"t":"bronte"},{"g":"βροντόφωνος","r":[{"c":"громогласный","e":"громоглaсный","i":4348}],"t":"brontophonos"},{"g":"βροῦχος","r":[{"c":"гусеница","e":"гyсеница","i":4366}],"t":"brouchos"},{"g":"βρυαίνη","r":[{"c":"вриена","e":"врmeна","i":3483}],"t":"bryaine"},{"g":"βρωτόν","r":[{"c":"брашно","e":"брaшно","i":1931}],"t":"broton"},{"g":"βρύαινα","r":[{"c":"вриена","e":"врmeна","i":3483}],"t":"bryaina"},{"g":"βρύχω","r":[{"c":"возскрежетати","e":"возскрежетaти","i":3138}],"t":"brycho"},{"g":"βρύω","r":[{"c":"врети","e":"врёти","i":3481}],"t":"bryo"},{"g":"βρῶμα","r":[{"c":"брашно","e":"брaшно","i":1931}],"t":"broma"},{"g":"βρῶσις","r":[{"c":"вкус","e":"вкyсъ","i":2713},{"c":"вкушение","e":"вкушeніе","i":2717}],"t":"brosis"}]}