{"i":"mst","r":[{"t":"dynamenos","r":[{"e":"всемогyщій","c":"всемогущий","i":3618}],"g":"δυνάμενος"},{"t":"dynastes","r":[{"e":"вельм0жа","c":"вельможа","i":2547}],"g":"δυνάστης"},{"t":"dynamoumai","r":[{"e":"возмогaти","c":"возмогати","i":3059}],"g":"δυναμοῦμαι"},{"t":"dynata","r":[{"e":"возм0жный","c":"возможный","i":3061}],"g":"δυνατά"},{"t":"dynaton","r":[{"e":"возм0жнw","c":"возможно","i":6071}],"g":"δυνατόν"},{"t":"dynatos","r":[{"e":"вмэсти1тельно","c":"вместительно","i":6095}],"g":"δυνατός"},{"t":"dynamai","r":[{"e":"возмогaти","c":"возмогати","i":3059},{"e":"возмощи2","c":"возмощи","i":3062}],"g":"δύναμαι"},{"t":"dynamis","r":[{"e":"в0и","c":"вои","i":3192}],"g":"δύναμις"}]}