{"i":"rtu","r":[{"t":"enkathormizo","r":[{"e":"возвести2","c":"возвести","i":2896}],"g":"ἐγκαθορμίζω"},{"t":"enkarsios","r":[{"e":"вопреки2","c":"вопреки","i":3261}],"g":"ἐγκαρσίως"},{"t":"enkatapegnymi","r":[{"e":"вонзи1ти","c":"вонзити","i":3226}],"g":"ἐγκαταπήγνυμι"},{"t":"enkatoikizomai","r":[{"e":"вселsтисz","c":"вселятися","i":3613}],"g":"ἐγκατοικίζομαι"},{"t":"enkauchaomai","r":[{"e":"восхвали1тисz","c":"восхвалитися","i":3399}],"g":"ἐνκαυχάομαι"},{"t":"enkaton","r":[{"e":"внyтренній","c":"внутренний","i":2812}],"g":"ἔγκατον"}]}