{"i":"cnt","r":[{"t":"eumeneia","r":[{"e":"благосeрдіе","c":"благосердие","i":1116}],"g":"εὐμένεια"},{"t":"eumechanos","r":[{"e":"благохи1тростный","c":"благохитростный","i":2011}],"g":"εὐμήχανος"},{"t":"eumenes","r":[{"e":"благопребhтный","c":"благопребытный","i":656},{"e":"благопріeмный","c":"благоприемный","i":699},{"e":"благосeрдный","c":"благосердный","i":1118},{"e":"благосeрдый","c":"благосердый","i":1119},{"e":"благочeстный","c":"благочестный","i":1910}],"g":"εὐμενής"},{"t":"eumenos","r":[{"e":"благопребhтнw","c":"благопребытно","i":2258},{"e":"благопріeмнэ","c":"благоприемне","i":700},{"e":"благопріsтнw","c":"благоприятно","i":703},{"e":"благосeрднw","c":"благосердно","i":1117}],"g":"εὐμενῶς"},{"t":"eumetadotos","r":[{"e":"благоподaтливый","c":"благоподатливый","i":2115}],"g":"εὐμετάδοτος"}]}