{"r":[{"t":"eustatheia","r":[{"e":"благостоsніе","i":511,"c":"благостояние"}],"g":"εὐστάθεια"},{"t":"eustatheo","r":[{"e":"благостоsніе","i":511,"c":"благостояние"}],"g":"εὐσταθέω"},{"t":"eustathes","r":[{"e":"благостоsнный","i":513,"c":"благостоянный"},{"e":"благоукрашeнный","i":729,"c":"благоукрашенный"}],"g":"εὐσταθής"},{"t":"eustathos","r":[{"e":"благостоsтельнэ","i":1409,"c":"благостоятельне"}],"g":"εὐσταθῶς"},{"t":"eustales","r":[{"e":"благомyжественный","i":2231,"c":"благомужественный"},{"e":"благоwдeждный","i":2175,"c":"благоодеждный"}],"g":"εὐσταλής"},{"t":"eustalos","r":[{"e":"благоwпрsтнw","i":2176,"c":"благоопрятно"},{"e":"благостоsннw","i":512,"c":"благостоянно"}],"g":"εὐσταλῶς"},{"t":"eustochos","r":[{"e":"благоуг0дный","i":1938,"c":"благоугодный"}],"g":"εὐστοχός"},{"t":"eustrophia","r":[{"e":"благоwбращeніе","i":1415,"c":"благообращение"}],"g":"εὐστροφία"},{"t":"eustochos","r":[{"e":"благополyчнw","i":1982,"c":"благополучно"}],"g":"εὐστόχως"},{"t":"eustathmos","r":[{"e":"благостоsнный","i":513,"c":"благостоянный"}],"g":"εὔσταθμος"},{"t":"eustachys","r":[{"e":"благоклaсный","i":2109,"c":"благокласный"}],"g":"εὔσταχυς"},{"t":"eustochos","r":[{"e":"благополyчный","i":1981,"c":"благополучный"}],"g":"εὔστοχος"}],"i":"aor"}