{"i":"aeilors","r":[{"g":"εὐπάθεια","r":[{"i":514,"c":"благострастие","e":"благострaстіе"}],"t":"eupatheia"},{"g":"εὐπαθέω","r":[{"i":2155,"c":"благоприимати","e":"благопріимaти"}],"t":"eupatheo"},{"g":"εὐπαρρησίαστος","r":[{"i":2218,"c":"благодерзновенный","e":"благодерзновeнный"}],"t":"euparrhesiastos"},{"g":"εὐπαρρησιάστος","r":[{"i":2218,"c":"благодерзновенный","e":"благодерзновeнный"}],"t":"euparrhesiastos"},{"g":"εὐπείθεια","r":[{"i":1969,"c":"благопокорение","e":"благопокорeніе"}],"t":"eupeitheia"},{"g":"εὐπειθέω","r":[{"i":2139,"c":"благоповиноватися","e":"благоповиновaтисz"}],"t":"eupeitheo"},{"g":"εὐπειθής","r":[{"i":1980,"c":"благопокоривый","e":"благопокори1вый"},{"i":2117,"c":"благопокорливый","e":"благопокорли1вый"},{"i":2015,"c":"благопокорный","e":"благопок0рный"}],"t":"eupeithes"},{"g":"εὐπειθῶς","r":[{"i":2113,"c":"благопокориво","e":"благопокори1вw"},{"i":2014,"c":"благопокорне","e":"благопок0рнэ"},{"i":981,"c":"благопокорно","e":"благопок0рнw"}],"t":"eupeithos"},{"g":"εὐπιστία","r":[{"i":1424,"c":"благоверие","e":"благовёріе"}],"t":"eupistia"},{"g":"εὐπλόως","r":[{"i":2082,"c":"благоплавно","e":"благоплaвнw"}],"t":"euploos"},{"g":"εὐπορέω","r":[{"i":905,"c":"благоисточити","e":"благоисточи1ти"},{"i":2174,"c":"благообительствовати","e":"благоwби1тельствовати"},{"i":3062,"c":"возмощи","e":"возмощи2"}],"t":"euporeo"},{"g":"εὐπορῶ","r":[{"i":1057,"c":"богатети","e":"богатёти"}],"t":"euporo"},{"g":"εὐπρέπεια","r":[{"i":1956,"c":"благолепие","e":"благолёпіе"},{"i":728,"c":"благоукрашение","e":"благоукрашeніе"}],"t":"euprepeia"},{"g":"εὐπρεπέστατα","r":[{"i":2105,"c":"благолепне","e":"благолёпнэ"}],"t":"euprepestata"},{"g":"εὐπρεπής","r":[{"i":1917,"c":"благолепный","e":"благолёпный"},{"i":1303,"c":"боголепный","e":"боголёпный"}],"t":"euprepes"},{"g":"εὐπρεπεία","r":[{"i":1956,"c":"благолепие","e":"благолёпіе"}],"t":"euprepeia"},{"g":"εὐπρεπεστάτως","r":[{"i":2105,"c":"благолепне","e":"благолёпнэ"}],"t":"euprepestatos"},{"g":"εὐπρεπῶς","r":[{"i":2079,"c":"благолепно","e":"благолёпнw"},{"i":1564,"c":"боголепне","e":"боголёпнэ"}],"t":"euprepos"},{"g":"εὐπροσήγορος","r":[{"i":2126,"c":"благозванный","e":"благозвaнный"},{"i":2262,"c":"благоприветливый","e":"благопривётливый"}],"t":"euprosegoros"},{"g":"εὐπρόσδεκτος","r":[{"i":1909,"c":"благоприятный","e":"благопріsтный"}],"t":"euprosdektos"},{"g":"εὐπρόσωπος","r":[{"i":908,"c":"благоличный","e":"благоли1чный"}],"t":"euprosopos"},{"g":"εὐψυχία","r":[{"i":1441,"c":"благодушие","e":"благодyшіе"}],"t":"eupsychia"},{"g":"εὐψύχως","r":[{"i":1442,"c":"благодушно","e":"благодyшнw"}],"t":"eupsychos"}]}