{"i":"l","r":[{"g":"φιλάγαθος","r":[{"c":"благолюбец","e":"благолю1бецъ","i":978},{"c":"благолюбивый","e":"благолюби1вый","i":2016}],"t":"philagathos"},{"g":"φιλάδελφος","r":[{"c":"братолюбец","e":"братолю1бецъ","i":554}],"t":"philadelphos"},{"g":"φιλαδελφία","r":[{"c":"братолюбие","e":"братолю1біе","i":555}],"t":"philadelphia"},{"g":"φιλοθέως","r":[{"c":"боголюбезно","e":"боголюбeзнw","i":1587}],"t":"philotheos"},{"g":"φιλόθεος","r":[{"c":"боголюбезный","e":"боголюбeзный","i":1585},{"c":"боголюбец","e":"боголю1бецъ","i":1588},{"c":"боголюбивый","e":"боголюби1вый","i":1589},{"c":"боголюбный","e":"боголю1бный","i":1593}],"t":"philotheos"}]}