{"i":"aeioy","r":[{"r":[{"i":2439,"c":"ваиа","e":"вaіа"},{"i":2527,"c":"веие","e":"вёіе"},{"i":2327,"c":"ветвие","e":"вётвіе"},{"i":2326,"c":"ветвь","e":"вётвь"}],"t":"klados","g":"κλάδος"},{"r":[{"i":411,"c":"бегство","e":"бёгство"}],"t":"klino","g":"κλίνω"},{"r":[{"i":3025,"c":"возлежание","e":"возлежaніе"}],"t":"klisis","g":"κλίσις"},{"r":[{"i":3328,"c":"восплакатися","e":"восплaкатисz"}],"t":"klaio","g":"κλαίω"},{"r":[{"i":1550,"c":"бракоокрадованная","e":"бракоwкрaдованнаz"}],"t":"klepsigamos","g":"κλεψίγαμος"},{"r":[{"i":2377,"c":"волхвование","e":"волхвовaніе"}],"t":"kledonismos","g":"κληδονισμός"},{"r":[{"i":1937,"c":"бремя","e":"брeмz"}],"t":"kloios","g":"κλοιός"},{"r":[{"i":2747,"c":"влатися","e":"влaтисz"},{"i":4561,"c":"возволноватися","e":"возволновaтисz"}],"t":"klydonizomai","g":"κλυδωνίζομαι"},{"r":[{"i":2734,"c":"влати","e":"влaти"}],"t":"klydonizo","g":"κλυδωνίζω"},{"r":[{"i":1451,"c":"буря","e":"бyрz"},{"i":3068,"c":"возмущение","e":"возмущeніе"},{"c":"волна","e":"волнA","g":"волна","i":2300,"o":1,"p":"сущ."}],"t":"klydon","g":"κλύδων"},{"r":[{"i":3013,"c":"воззвание","e":"воззвaніе"}],"t":"klesis","g":"κλῆσις"}]}