{"r":[{"r":[{"c":"возсияти","i":3134,"e":"возсіsти"}],"t":"lampo","g":"λάμπω"},{"r":[{"c":"вещати","i":2634,"e":"вэщaти"},{"c":"вопити","i":3254,"e":"вопи1ти"}],"t":"lego","g":"λέγω"},{"r":[{"c":"блеск","i":1139,"e":"блeскъ"}],"t":"lepra","g":"λέπρα"},{"r":[{"c":"блядивый","i":1156,"e":"блzди1вый"},{"c":"блядь","i":1155,"e":"блsдь"}],"t":"leros","g":"λήρος"},{"r":[{"o":1,"c":"а","g":"буква","i":1394,"e":"а"}],"t":"la","g":"λα'"},{"r":[{"c":"вручити","i":3490,"e":"вручи1ти"}],"t":"lanchano","g":"λαγχάνω"},{"r":[{"c":"бок","i":1170,"e":"б0къ"}],"t":"lagon","g":"λαγών"},{"r":[{"c":"возглаголати","i":2929,"e":"возглаг0лати"}],"t":"laleo","g":"λαλέω"},{"r":[{"c":"велеречие","i":1513,"e":"велерёчіе"}],"t":"lalia","g":"λαλία"},{"r":[{"c":"беседа","i":1724,"e":"бесёда"},{"c":"весть","i":2616,"e":"вёсть"}],"t":"lalia","g":"λαλιά"},{"r":[{"c":"возглаголатися","i":2930,"e":"возглаг0латисz"}],"t":"laloumai","g":"λαλοῦμαι"},{"r":[{"c":"взятися","i":2667,"e":"взsтисz"}],"t":"lambanomai","g":"λαμβάνομαι"},{"r":[{"c":"взимати","i":2660,"e":"взимaти"},{"c":"взиматися","i":2661,"e":"взимaтисz"},{"c":"взяти","i":2666,"e":"взsти"},{"c":"восприяти","i":3353,"e":"воспріsти"}],"t":"lambano","g":"λαμβάνω"},{"r":[{"c":"восток","i":3381,"e":"вост0къ"}],"t":"lamprotes","g":"λαμπρότης"},{"r":[{"c":"буря","i":1451,"e":"бyрz"},{"c":"ветр","i":2328,"e":"вётръ"},{"c":"вихр","i":2705,"e":"ви1хръ"}],"t":"lailaps","g":"λαῖλαψ"},{"r":[{"c":"верт","i":1488,"e":"вeртъ"},{"c":"вертоград","i":2597,"e":"вертогрaдъ"}],"t":"leimon","g":"λειμών"},{"r":[{"c":"белоодеждный","i":1999,"e":"бэлоoдeждный"}],"t":"leukeimon","g":"λευκείμων"},{"r":[{"c":"белоносный","i":1459,"e":"бэлон0сный"}],"t":"leukophoros","g":"λευκοφόρος"},{"r":[{"c":"белый","i":471,"e":"бёлый"}],"t":"leukos","g":"λευκός"},{"r":[{"c":"белость","i":113,"e":"бёлость"}],"t":"leukotes","g":"λευκότης"},{"r":[{"c":"белообразный","i":458,"e":"бэлоwбрaзный"}],"t":"leucheimon","g":"λευχείμων"},{"r":[{"c":"белообразовати","i":470,"e":"бэлоwбразовaти"}],"t":"leucheimono","g":"λευχειμονῶ"},{"r":[{"c":"белоносяй","i":459,"e":"бэлоносsй"},{"c":"белообразне","i":468,"e":"бэлоoбрaзнэ"}],"t":"leucheimonon","g":"λευχειμονῶν"},{"r":[{"c":"буесловящий","i":1083,"e":"буесл0вzщій"}],"t":"lerodes","g":"ληρώδης"},{"r":[{"c":"ваяти","i":2508,"e":"ваsти"}],"t":"lithourgeomai","g":"λιθουργέομαι"},{"r":[{"c":"веятися","i":4499,"e":"вёzтисz"}],"t":"likmaomai","g":"λικμάομαι"},{"r":[{"c":"веяти","i":2635,"e":"вёzти"},{"c":"возвеяти","i":2904,"e":"возвёzти"}],"t":"likmao","g":"λικμάω"},{"r":[{"c":"веятель","i":4522,"e":"вёzтель"}],"t":"likmetor","g":"λικμήτωρ"},{"r":[{"c":"веяло","i":4521,"e":"вёzло"}],"t":"likmos","g":"λικμός"},{"r":[{"c":"алчба","i":137,"e":"ѓлчба"}],"t":"limos","g":"λιμός"}],"i":"aeioy"}