{"r":[{"t":"prosagomai","g":"προσάγομαι","r":[{"i":2797,"e":"внести1сz","c":"внестися"}]},{"t":"prosangellomai","g":"προσαγγέλλομαι","r":[{"i":2900,"e":"возвэсти1тисz","c":"возвеститися"}]},{"t":"prosanabasis","g":"προσανάβασις","r":[{"i":3414,"e":"восхождeніе","c":"восхождение"}]},{"t":"prosanaptomai","g":"προσανάπτομαι","r":[{"i":2640,"e":"вжещи1сz","c":"вжещися"}]},{"t":"prosanapto","g":"προσανάπτω","r":[{"i":2642,"e":"вжигaти","c":"вжигати"}]},{"t":"prosanecho","g":"προσανέχω","r":[{"i":2806,"e":"внимaти","c":"внимати"}]},{"t":"prosanaklinomai","g":"προσανακλίνομαι","r":[{"i":3029,"e":"возлещи2","c":"возлещи"}]}],"i":"gn"}