{"r":[{"t":"prepei","r":[{"e":"вёдомо","i":2520,"c":"ведомо"}],"g":"πρέπει"},{"t":"prosphatos","r":[{"e":"вн0вэ","i":4541,"c":"внове"}],"g":"προ­σφάτως"},{"t":"prosotheo","r":[{"e":"врэsти","i":4646,"c":"вреяти"}],"g":"προ­σωθέω"},{"t":"proiemai","r":[{"e":"вдаsти","i":1238,"c":"вдаяти"}],"g":"προΐεμαι"},{"t":"proago","r":[{"g":"предварять","c":"варити","p":"гл.","e":"вари1ти","i":2472,"o":1},{"e":"варsти","i":2488,"c":"варяти"}],"g":"προάγω"},{"t":"proegoumenos","r":[{"e":"воев0да","i":2853,"c":"воевода"}],"g":"προηγούμενος"},{"t":"prothymeomai","r":[{"e":"воз8усeрдствовати","i":3170,"c":"возусердствовати"}],"g":"προθυμέομαι"},{"t":"prokaloumai","r":[{"e":"воврещи1сz","i":1465,"c":"воврещися"}],"g":"προκαλοῦμαι"},{"t":"prokindyneuo","r":[{"e":"бёдствовати","i":407,"c":"бедствовати"}],"g":"προκινδυνεύω"},{"t":"propetes","r":[{"e":"безчи1нный","i":460,"c":"безчинный"}],"g":"προπετής"},{"t":"prosagomai","r":[{"e":"внести1сz","i":2797,"c":"внестися"}],"g":"προσάγομαι"},{"t":"proserchomai","r":[{"e":"входи1ти","i":3816,"c":"входити"}],"g":"προσέρχομαι"},{"t":"prosechomai","r":[{"e":"внимaти","i":2806,"c":"внимати"}],"g":"προσέχομαι"},{"t":"prosecho","r":[{"e":"внимaти","i":2806,"c":"внимати"},{"e":"внsти","i":2820,"c":"вняти"}],"g":"προσέχω"},{"t":"prosangellomai","r":[{"e":"возвэсти1тисz","i":2900,"c":"возвеститися"}],"g":"προσαγγέλλομαι"},{"t":"prosanabasis","r":[{"e":"восхождeніе","i":3414,"c":"восхождение"}],"g":"προσανάβασις"},{"t":"prosanaptomai","r":[{"e":"вжещи1сz","i":2640,"c":"вжещися"}],"g":"προσανάπτομαι"},{"t":"prosanapto","r":[{"e":"вжигaти","i":2642,"c":"вжигати"}],"g":"προσανάπτω"},{"t":"prosanecho","r":[{"e":"внимaти","i":2806,"c":"внимати"}],"g":"προσανέχω"},{"t":"prosanaklinomai","r":[{"e":"возлещи2","i":3029,"c":"возлещи"}],"g":"προσανακλίνομαι"},{"t":"prosdeomai","r":[{"e":"вострeбовати","i":3388,"c":"востребовати"}],"g":"προσδέομαι"},{"t":"prosdechomai","r":[{"e":"воспріsти","i":3353,"c":"восприяти"}],"g":"προσδέχομαι"},{"t":"prosdokiananaphero","r":[{"e":"возноси1ти","i":3082,"c":"возносити"}],"g":"προσδοκίαν...ἀναφέρω"},{"t":"prosektikos","r":[{"e":"внимaтельный","i":2805,"c":"внимательный"}],"g":"προσεκτικός"},{"t":"prosepanapto","r":[{"e":"возжизaти","i":3011,"c":"возжизати"}],"g":"προσεπανάπτω"},{"t":"prosechontos","r":[{"e":"внимaтельнw","i":2804,"c":"внимательно"}],"g":"προσεχόντως"},{"t":"proskairos","r":[{"e":"врeменнw","i":2343,"c":"временно"}],"g":"προσκαίρως"},{"t":"proskephalaion","r":[{"e":"возглaвіе","i":2926,"c":"возглавие"},{"e":"возглaвійца","i":4565,"c":"возглавийца"},{"e":"возглaвница","i":2928,"c":"возглавница"}],"g":"προσκεφάλαιον"},{"t":"proskylizo","r":[{"e":"возвали1ти","i":2885,"c":"возвалити"}],"g":"προσκυλίζω"},{"t":"proslalo","r":[{"e":"бесёдовати","i":876,"c":"беседовати"}],"g":"προσλαλῶ"}],"i":"aeo"}